aliyunsdkrds/__init__.py
aliyunsdkrds/endpoint.py
aliyunsdkrds/request/__init__.py
aliyunsdkrds/request/v20140815/AcceptRCInquiredSystemEventRequest.py
aliyunsdkrds/request/v20140815/ActivateMigrationTargetInstanceRequest.py
aliyunsdkrds/request/v20140815/AddTagsToResourceRequest.py
aliyunsdkrds/request/v20140815/AllocateInstancePublicConnectionRequest.py
aliyunsdkrds/request/v20140815/AllocateReadWriteSplittingConnectionRequest.py
aliyunsdkrds/request/v20140815/AssociateEipAddressWithRCInstanceRequest.py
aliyunsdkrds/request/v20140815/AttachRCDiskRequest.py
aliyunsdkrds/request/v20140815/AttachRCInstancesRequest.py
aliyunsdkrds/request/v20140815/AttachWhitelistTemplateToInstanceRequest.py
aliyunsdkrds/request/v20140815/AuthorizeRCSecurityGroupPermissionRequest.py
aliyunsdkrds/request/v20140815/CalculateDBInstanceWeightRequest.py
aliyunsdkrds/request/v20140815/CancelActiveOperationTasksRequest.py
aliyunsdkrds/request/v20140815/CheckAccountNameAvailableRequest.py
aliyunsdkrds/request/v20140815/CheckCloudResourceAuthorizedRequest.py
aliyunsdkrds/request/v20140815/CheckCreateDdrDBInstanceRequest.py
aliyunsdkrds/request/v20140815/CheckDBNameAvailableRequest.py
aliyunsdkrds/request/v20140815/CheckInstanceExistRequest.py
aliyunsdkrds/request/v20140815/CheckServiceLinkedRoleRequest.py
aliyunsdkrds/request/v20140815/CloneDBInstanceRequest.py
aliyunsdkrds/request/v20140815/CloneParameterGroupRequest.py
aliyunsdkrds/request/v20140815/ConfirmNotifyRequest.py
aliyunsdkrds/request/v20140815/CopyDatabaseBetweenInstancesRequest.py
aliyunsdkrds/request/v20140815/CopyDatabaseRequest.py
aliyunsdkrds/request/v20140815/CreateAccountRequest.py
aliyunsdkrds/request/v20140815/CreateBackupRequest.py
aliyunsdkrds/request/v20140815/CreateCloudMigrationPrecheckTaskRequest.py
aliyunsdkrds/request/v20140815/CreateCloudMigrationTaskRequest.py
aliyunsdkrds/request/v20140815/CreateDBInstanceEndpointAddressRequest.py
aliyunsdkrds/request/v20140815/CreateDBInstanceEndpointRequest.py
aliyun_python_sdk_rds-2.7.53.dist-info/LICENSE
aliyun_python_sdk_rds-2.7.53.dist-info/METADATA
aliyun_python_sdk_rds-2.7.53.dist-info/WHEEL
aliyun_python_sdk_rds-2.7.53.dist-info/top_level.txt
aliyun_python_sdk_rds-2.7.53.dist-info/RECORD
